{"nodes": [{"id": "c_users_arnel_glenn_jimenez_devfiles_mc_mods_mc_battlepass_docs_context_lean_ctx_md", "label": "lean-ctx.md", "file_type": "document", "source_file": "C:\\Users\\Arnel Glenn Jimenez\\devfiles\\mc-mods\\mc-battlepass\\docs\\context\\lean-ctx.md", "source_location": "L1"}, {"id": "context_lean_ctx_leanctx", "label": "LeanCTX", "file_type": "document", "source_file": "C:\\Users\\Arnel Glenn Jimenez\\devfiles\\mc-mods\\mc-battlepass\\docs\\context\\lean-ctx.md", "source_location": "L1"}, {"id": "context_lean_ctx_install", "label": "Install", "file_type": "document", "source_file": "C:\\Users\\Arnel Glenn Jimenez\\devfiles\\mc-mods\\mc-battlepass\\docs\\context\\lean-ctx.md", "source_location": "L5"}, {"id": "context_lean_ctx_codeblock_1", "label": "code:bash (curl -fsSL https://leanctx.com/install.sh | sh)", "file_type": "document", "source_file": "C:\\Users\\Arnel Glenn Jimenez\\devfiles\\mc-mods\\mc-battlepass\\docs\\context\\lean-ctx.md", "source_location": "L9"}, {"id": "context_lean_ctx_setup", "label": "Setup", "file_type": "document", "source_file": "C:\\Users\\Arnel Glenn Jimenez\\devfiles\\mc-mods\\mc-battlepass\\docs\\context\\lean-ctx.md", "source_location": "L16"}, {"id": "context_lean_ctx_codeblock_2", "label": "code:bash (lean-ctx setup)", "file_type": "document", "source_file": "C:\\Users\\Arnel Glenn Jimenez\\devfiles\\mc-mods\\mc-battlepass\\docs\\context\\lean-ctx.md", "source_location": "L18"}, {"id": "context_lean_ctx_pi_package_path", "label": "Pi Package Path", "file_type": "document", "source_file": "C:\\Users\\Arnel Glenn Jimenez\\devfiles\\mc-mods\\mc-battlepass\\docs\\context\\lean-ctx.md", "source_location": "L25"}, {"id": "context_lean_ctx_codeblock_3", "label": "code:bash (pi install npm:pi-lean-ctx -l)", "file_type": "document", "source_file": "C:\\Users\\Arnel Glenn Jimenez\\devfiles\\mc-mods\\mc-battlepass\\docs\\context\\lean-ctx.md", "source_location": "L27"}, {"id": "context_lean_ctx_useful_commands", "label": "Useful Commands", "file_type": "document", "source_file": "C:\\Users\\Arnel Glenn Jimenez\\devfiles\\mc-mods\\mc-battlepass\\docs\\context\\lean-ctx.md", "source_location": "L31"}, {"id": "context_lean_ctx_codeblock_4", "label": "code:bash (lean-ctx read AGENTS.md -m map)", "file_type": "document", "source_file": "C:\\Users\\Arnel Glenn Jimenez\\devfiles\\mc-mods\\mc-battlepass\\docs\\context\\lean-ctx.md", "source_location": "L33"}, {"id": "context_lean_ctx_escape_hatches", "label": "Escape Hatches", "file_type": "document", "source_file": "C:\\Users\\Arnel Glenn Jimenez\\devfiles\\mc-mods\\mc-battlepass\\docs\\context\\lean-ctx.md", "source_location": "L40"}, {"id": "context_lean_ctx_codeblock_5", "label": "code:bash (lean-ctx-off)", "file_type": "document", "source_file": "C:\\Users\\Arnel Glenn Jimenez\\devfiles\\mc-mods\\mc-battlepass\\docs\\context\\lean-ctx.md", "source_location": "L42"}], "edges": [{"source": "c_users_arnel_glenn_jimenez_devfiles_mc_mods_mc_battlepass_docs_context_lean_ctx_md", "target": "context_lean_ctx_leanctx", "relation": "contains", "confidence": "EXTRACTED", "source_file": "C:\\Users\\Arnel Glenn Jimenez\\devfiles\\mc-mods\\mc-battlepass\\docs\\context\\lean-ctx.md", "source_location": "L1", "weight": 1.0}, {"source": "context_lean_ctx_leanctx", "target": "context_lean_ctx_install", "relation": "contains", "confidence": "EXTRACTED", "source_file": "C:\\Users\\Arnel Glenn Jimenez\\devfiles\\mc-mods\\mc-battlepass\\docs\\context\\lean-ctx.md", "source_location": "L5", "weight": 1.0}, {"source": "context_lean_ctx_install", "target": "context_lean_ctx_codeblock_1", "relation": "contains", "confidence": "EXTRACTED", "source_file": "C:\\Users\\Arnel Glenn Jimenez\\devfiles\\mc-mods\\mc-battlepass\\docs\\context\\lean-ctx.md", "source_location": "L9", "weight": 1.0}, {"source": "context_lean_ctx_leanctx", "target": "context_lean_ctx_setup", "relation": "contains", "confidence": "EXTRACTED", "source_file": "C:\\Users\\Arnel Glenn Jimenez\\devfiles\\mc-mods\\mc-battlepass\\docs\\context\\lean-ctx.md", "source_location": "L16", "weight": 1.0}, {"source": "context_lean_ctx_setup", "target": "context_lean_ctx_codeblock_2", "relation": "contains", "confidence": "EXTRACTED", "source_file": "C:\\Users\\Arnel Glenn Jimenez\\devfiles\\mc-mods\\mc-battlepass\\docs\\context\\lean-ctx.md", "source_location": "L18", "weight": 1.0}, {"source": "context_lean_ctx_leanctx", "target": "context_lean_ctx_pi_package_path", "relation": "contains", "confidence": "EXTRACTED", "source_file": "C:\\Users\\Arnel Glenn Jimenez\\devfiles\\mc-mods\\mc-battlepass\\docs\\context\\lean-ctx.md", "source_location": "L25", "weight": 1.0}, {"source": "context_lean_ctx_pi_package_path", "target": "context_lean_ctx_codeblock_3", "relation": "contains", "confidence": "EXTRACTED", "source_file": "C:\\Users\\Arnel Glenn Jimenez\\devfiles\\mc-mods\\mc-battlepass\\docs\\context\\lean-ctx.md", "source_location": "L27", "weight": 1.0}, {"source": "context_lean_ctx_leanctx", "target": "context_lean_ctx_useful_commands", "relation": "contains", "confidence": "EXTRACTED", "source_file": "C:\\Users\\Arnel Glenn Jimenez\\devfiles\\mc-mods\\mc-battlepass\\docs\\context\\lean-ctx.md", "source_location": "L31", "weight": 1.0}, {"source": "context_lean_ctx_useful_commands", "target": "context_lean_ctx_codeblock_4", "relation": "contains", "confidence": "EXTRACTED", "source_file": "C:\\Users\\Arnel Glenn Jimenez\\devfiles\\mc-mods\\mc-battlepass\\docs\\context\\lean-ctx.md", "source_location": "L33", "weight": 1.0}, {"source": "context_lean_ctx_leanctx", "target": "context_lean_ctx_escape_hatches", "relation": "contains", "confidence": "EXTRACTED", "source_file": "C:\\Users\\Arnel Glenn Jimenez\\devfiles\\mc-mods\\mc-battlepass\\docs\\context\\lean-ctx.md", "source_location": "L40", "weight": 1.0}, {"source": "context_lean_ctx_escape_hatches", "target": "context_lean_ctx_codeblock_5", "relation": "contains", "confidence": "EXTRACTED", "source_file": "C:\\Users\\Arnel Glenn Jimenez\\devfiles\\mc-mods\\mc-battlepass\\docs\\context\\lean-ctx.md", "source_location": "L42", "weight": 1.0}], "input_tokens": 0, "output_tokens": 0}