{"nodes": [{"id": "c_users_arnel_glenn_jimenez_devfiles_mc_mods_mc_battlepass_docs_ckdm_balance_md", "label": "CKDM_BALANCE.md", "file_type": "document", "source_file": "C:\\Users\\Arnel Glenn Jimenez\\devfiles\\mc-mods\\mc-battlepass\\docs\\CKDM_BALANCE.md", "source_location": "L1"}, {"id": "docs_ckdm_balance_ckdm_balance", "label": "CKDM Balance", "file_type": "document", "source_file": "C:\\Users\\Arnel Glenn Jimenez\\devfiles\\mc-mods\\mc-battlepass\\docs\\CKDM_BALANCE.md", "source_location": "L1"}, {"id": "docs_ckdm_balance_generated_configs", "label": "Generated Configs", "file_type": "document", "source_file": "C:\\Users\\Arnel Glenn Jimenez\\devfiles\\mc-mods\\mc-battlepass\\docs\\CKDM_BALANCE.md", "source_location": "L5"}, {"id": "docs_ckdm_balance_codeblock_1", "label": "code:powershell (.\\scripts\\generate-ckdm-balance.ps1)", "file_type": "document", "source_file": "C:\\Users\\Arnel Glenn Jimenez\\devfiles\\mc-mods\\mc-battlepass\\docs\\CKDM_BALANCE.md", "source_location": "L9"}, {"id": "docs_ckdm_balance_battlepass_shape", "label": "Battlepass Shape", "file_type": "document", "source_file": "C:\\Users\\Arnel Glenn Jimenez\\devfiles\\mc-mods\\mc-battlepass\\docs\\CKDM_BALANCE.md", "source_location": "L29"}, {"id": "docs_ckdm_balance_relic_token_placement", "label": "Relic Token Placement", "file_type": "document", "source_file": "C:\\Users\\Arnel Glenn Jimenez\\devfiles\\mc-mods\\mc-battlepass\\docs\\CKDM_BALANCE.md", "source_location": "L39"}, {"id": "docs_ckdm_balance_elytra_gate", "label": "Elytra Gate", "file_type": "document", "source_file": "C:\\Users\\Arnel Glenn Jimenez\\devfiles\\mc-mods\\mc-battlepass\\docs\\CKDM_BALANCE.md", "source_location": "L50"}, {"id": "docs_ckdm_balance_tech_mod_gates", "label": "Tech Mod Gates", "file_type": "document", "source_file": "C:\\Users\\Arnel Glenn Jimenez\\devfiles\\mc-mods\\mc-battlepass\\docs\\CKDM_BALANCE.md", "source_location": "L57"}, {"id": "docs_ckdm_balance_xp_bands", "label": "XP Bands", "file_type": "document", "source_file": "C:\\Users\\Arnel Glenn Jimenez\\devfiles\\mc-mods\\mc-battlepass\\docs\\CKDM_BALANCE.md", "source_location": "L67"}, {"id": "docs_ckdm_balance_excluded_from_normal_pass_rewards", "label": "Excluded From Normal Pass Rewards", "file_type": "document", "source_file": "C:\\Users\\Arnel Glenn Jimenez\\devfiles\\mc-mods\\mc-battlepass\\docs\\CKDM_BALANCE.md", "source_location": "L78"}, {"id": "docs_ckdm_balance_store_bands", "label": "Store Bands", "file_type": "document", "source_file": "C:\\Users\\Arnel Glenn Jimenez\\devfiles\\mc-mods\\mc-battlepass\\docs\\CKDM_BALANCE.md", "source_location": "L90"}], "edges": [{"source": "c_users_arnel_glenn_jimenez_devfiles_mc_mods_mc_battlepass_docs_ckdm_balance_md", "target": "docs_ckdm_balance_ckdm_balance", "relation": "contains", "confidence": "EXTRACTED", "source_file": "C:\\Users\\Arnel Glenn Jimenez\\devfiles\\mc-mods\\mc-battlepass\\docs\\CKDM_BALANCE.md", "source_location": "L1", "weight": 1.0}, {"source": "docs_ckdm_balance_ckdm_balance", "target": "docs_ckdm_balance_generated_configs", "relation": "contains", "confidence": "EXTRACTED", "source_file": "C:\\Users\\Arnel Glenn Jimenez\\devfiles\\mc-mods\\mc-battlepass\\docs\\CKDM_BALANCE.md", "source_location": "L5", "weight": 1.0}, {"source": "docs_ckdm_balance_generated_configs", "target": "docs_ckdm_balance_codeblock_1", "relation": "contains", "confidence": "EXTRACTED", "source_file": "C:\\Users\\Arnel Glenn Jimenez\\devfiles\\mc-mods\\mc-battlepass\\docs\\CKDM_BALANCE.md", "source_location": "L9", "weight": 1.0}, {"source": "docs_ckdm_balance_ckdm_balance", "target": "docs_ckdm_balance_battlepass_shape", "relation": "contains", "confidence": "EXTRACTED", "source_file": "C:\\Users\\Arnel Glenn Jimenez\\devfiles\\mc-mods\\mc-battlepass\\docs\\CKDM_BALANCE.md", "source_location": "L29", "weight": 1.0}, {"source": "docs_ckdm_balance_ckdm_balance", "target": "docs_ckdm_balance_relic_token_placement", "relation": "contains", "confidence": "EXTRACTED", "source_file": "C:\\Users\\Arnel Glenn Jimenez\\devfiles\\mc-mods\\mc-battlepass\\docs\\CKDM_BALANCE.md", "source_location": "L39", "weight": 1.0}, {"source": "docs_ckdm_balance_ckdm_balance", "target": "docs_ckdm_balance_elytra_gate", "relation": "contains", "confidence": "EXTRACTED", "source_file": "C:\\Users\\Arnel Glenn Jimenez\\devfiles\\mc-mods\\mc-battlepass\\docs\\CKDM_BALANCE.md", "source_location": "L50", "weight": 1.0}, {"source": "docs_ckdm_balance_ckdm_balance", "target": "docs_ckdm_balance_tech_mod_gates", "relation": "contains", "confidence": "EXTRACTED", "source_file": "C:\\Users\\Arnel Glenn Jimenez\\devfiles\\mc-mods\\mc-battlepass\\docs\\CKDM_BALANCE.md", "source_location": "L57", "weight": 1.0}, {"source": "docs_ckdm_balance_ckdm_balance", "target": "docs_ckdm_balance_xp_bands", "relation": "contains", "confidence": "EXTRACTED", "source_file": "C:\\Users\\Arnel Glenn Jimenez\\devfiles\\mc-mods\\mc-battlepass\\docs\\CKDM_BALANCE.md", "source_location": "L67", "weight": 1.0}, {"source": "docs_ckdm_balance_ckdm_balance", "target": "docs_ckdm_balance_excluded_from_normal_pass_rewards", "relation": "contains", "confidence": "EXTRACTED", "source_file": "C:\\Users\\Arnel Glenn Jimenez\\devfiles\\mc-mods\\mc-battlepass\\docs\\CKDM_BALANCE.md", "source_location": "L78", "weight": 1.0}, {"source": "docs_ckdm_balance_ckdm_balance", "target": "docs_ckdm_balance_store_bands", "relation": "contains", "confidence": "EXTRACTED", "source_file": "C:\\Users\\Arnel Glenn Jimenez\\devfiles\\mc-mods\\mc-battlepass\\docs\\CKDM_BALANCE.md", "source_location": "L90", "weight": 1.0}], "input_tokens": 0, "output_tokens": 0}